SolidityGuanfangWendangZhongwenban/README.md
SolidityGuanfangWendangZhongwenban/__init__.py
SolidityGuanfangWendangZhongwenban/__main__.py
SolidityGuanfangWendangZhongwenban/file.epub
SolidityGuanfangWendangZhongwenban/index.html
SolidityGuanfangWendangZhongwenban/css/__init__.py
SolidityGuanfangWendangZhongwenban/css/annotations.css
SolidityGuanfangWendangZhongwenban/css/main.css
SolidityGuanfangWendangZhongwenban/css/normalize.css
SolidityGuanfangWendangZhongwenban/css/popup.css
SolidityGuanfangWendangZhongwenban/font/__init__.py
SolidityGuanfangWendangZhongwenban/font/fontello.eot
SolidityGuanfangWendangZhongwenban/font/fontello.svg
SolidityGuanfangWendangZhongwenban/font/fontello.ttf
SolidityGuanfangWendangZhongwenban/font/fontello.woff
SolidityGuanfangWendangZhongwenban/img/__init__.py
SolidityGuanfangWendangZhongwenban/img/annotator-glyph-sprite.png
SolidityGuanfangWendangZhongwenban/img/annotator-icon-sprite.png
SolidityGuanfangWendangZhongwenban/img/apple-touch-icon.png
SolidityGuanfangWendangZhongwenban/img/cancelfullscreen.png
SolidityGuanfangWendangZhongwenban/img/close.png
SolidityGuanfangWendangZhongwenban/img/fullscreen.png
SolidityGuanfangWendangZhongwenban/img/loader.gif
SolidityGuanfangWendangZhongwenban/img/menu-icon.png
SolidityGuanfangWendangZhongwenban/img/save.png
SolidityGuanfangWendangZhongwenban/img/saved.png
SolidityGuanfangWendangZhongwenban/img/settings-s.png
SolidityGuanfangWendangZhongwenban/img/settings.png
SolidityGuanfangWendangZhongwenban/img/star.png
SolidityGuanfangWendangZhongwenban/js/__init__.py
SolidityGuanfangWendangZhongwenban/js/epub.js
SolidityGuanfangWendangZhongwenban/js/epub.min.js
SolidityGuanfangWendangZhongwenban/js/epub.min.map
SolidityGuanfangWendangZhongwenban/js/hooks.min.js
SolidityGuanfangWendangZhongwenban/js/hooks.min.map
SolidityGuanfangWendangZhongwenban/js/reader.js
SolidityGuanfangWendangZhongwenban/js/reader.js.map
SolidityGuanfangWendangZhongwenban/js/reader.min.js
solidity_guanfang_wendang_zhongwenban-2024.3.3.0.dist-info/METADATA
solidity_guanfang_wendang_zhongwenban-2024.3.3.0.dist-info/WHEEL
solidity_guanfang_wendang_zhongwenban-2024.3.3.0.dist-info/entry_points.txt
solidity_guanfang_wendang_zhongwenban-2024.3.3.0.dist-info/top_level.txt
solidity_guanfang_wendang_zhongwenban-2024.3.3.0.dist-info/RECORD
